numpycnn/__init__.py
numpycnn/example.py
numpycnn-1.7.dist-info/METADATA
numpycnn-1.7.dist-info/RECORD
numpycnn-1.7.dist-info/WHEEL
numpycnn-1.7.dist-info/top_level.txt
