Metadata-Version: 2.1
Name: numpycnn
Version: 1.7
Summary: Building CNN from Scratch using NumPy
Home-page: https://github.com/ahmedfgad/NumPyCNN
Author: Ahmed F. Gad
Author-email: ahmed.f.gad@gmail.com
License: UNKNOWN
Platform: UNKNOWN
Classifier: Programming Language :: Python :: 3
Classifier: License :: OSI Approved :: MIT License
Classifier: Operating System :: OS Independent
